cmip_ref_core/__init__.py
cmip_ref_core/constraints.py
cmip_ref_core/dataset_registry.py
cmip_ref_core/datasets.py
cmip_ref_core/env.py
cmip_ref_core/exceptions.py
cmip_ref_core/executor.py
cmip_ref_core/logging.py
cmip_ref_core/metrics.py
cmip_ref_core/providers.py
cmip_ref_core/py.typed
cmip_ref_core/pycmec/README.md
cmip_ref_core/pycmec/__init__.py
cmip_ref_core/pycmec/controlled_vocabulary.py
cmip_ref_core/pycmec/cv_cmip7_aft.yaml
cmip_ref_core/pycmec/metric.py
cmip_ref_core/pycmec/output.py
cmip_ref_core-0.4.1.dist-info/METADATA
cmip_ref_core-0.4.1.dist-info/WHEEL
cmip_ref_core-0.4.1.dist-info/licenses/LICENCE
cmip_ref_core-0.4.1.dist-info/licenses/NOTICE
cmip_ref_core-0.4.1.dist-info/RECORD
